{
    "EEGCoordinateSystem": "CapTrak",
    "EEGCoordinateUnits": "m",
    "EEGCoordinateSystemDescription": "The X-axis goes from the left preauricular point (LPA) through the right preauricular point (RPA). The Y-axis goes orthogonally to the X-axis through the nasion (NAS). The Z-axis goes orthogonally to the XY-plane through the vertex of the head. This corresponds to a \"RAS\" orientation with the origin of the coordinate system approximately between the ears. See Appendix VIII in the BIDS specification.",
    "AnatomicalLandmarkCoordinates": {
        "NAS": [
            -8.820411013980103e-18,
            0.0945788119117235,
            1.5407439555097887e-33
        ],
        "LPA": [
            -0.0855367875575072,
            7.977152681690564e-18,
            0.0
        ],
        "RPA": [
            0.07153159237945624,
            -6.6710295098672444e-18,
            0.0
        ]
    },
    "AnatomicalLandmarkCoordinateSystem": "CapTrak",
    "AnatomicalLandmarkCoordinateUnits": "m"
}
